square/__init__.py
square/main.py
vishwam_test-1.0.dist-info/LICENSE
vishwam_test-1.0.dist-info/METADATA
vishwam_test-1.0.dist-info/WHEEL
vishwam_test-1.0.dist-info/entry_points.txt
vishwam_test-1.0.dist-info/top_level.txt
vishwam_test-1.0.dist-info/RECORD
