Metadata-Version: 2.1
Name: vishwam-test
Version: 1.0
Summary: squares the number
Home-page: https://github.com/vishwamshuklaRazorpay/vishwam_test
Author: Vishwam
License: MIT
Platform: UNKNOWN
Classifier: License :: OSI Approved :: MIT License
Classifier: Programming Language :: Python :: 3.6
Classifier: Programming Language :: Python :: 3.7
Classifier: Programming Language :: Python :: 3.8
License-File: LICENSE
